edahelper/__init__.py
edahelper/core.py
edahelper/data_cleaning.py
edahelper/data_loading.py
edahelper/data_overview.py
edahelper/feature_engineering.py
edahelper/inspector.py
edahelper/nextstep.py
edahelper/show.py
edahelper/stats_summary.py
edahelper/tools.py
edahelper/ui.py
edahelper/visualization.py
pyedahelper-1.0.9.dist-info/licenses/LICENSE
pyedahelper-1.0.9.dist-info/METADATA
pyedahelper-1.0.9.dist-info/WHEEL
pyedahelper-1.0.9.dist-info/top_level.txt
pyedahelper-1.0.9.dist-info/RECORD
