Metadata-Version: 2.4
Name: pyedahelper
Version: 1.0.9
Summary: An interactive cheat sheet, AI-powered guide for exploratory data analysis (EDA), and tools for data visualization, cleaning and feature engineering.
Home-page: https://pypi.org/project/pyedahelper/
Author: Chidiebere V. Christopher
Author-email: vchidiebere.vc@gmail.com
License: MIT
Classifier: Programming Language :: Python :: 3
Classifier: License :: OSI Approved :: MIT License
Classifier: Operating System :: OS Independent
Classifier: Intended Audience :: Education
Classifier: Topic :: Scientific/Engineering :: Information Analysis
Requires-Python: >=3.7
License-File: LICENSE
Requires-Dist: pandas
Requires-Dist: numpy
Requires-Dist: matplotlib
Requires-Dist: seaborn
Requires-Dist: scikit-learn
Requires-Dist: rich
Dynamic: author
Dynamic: author-email
Dynamic: description
Dynamic: description-content-type
Dynamic: home-page
Dynamic: license
Dynamic: license-file
Dynamic: requires-dist
Dynamic: requires-python
Dynamic: summary
